LICENSE
MANIFEST.in
README
setup.py
block_snippets/__init__.py
block_snippets/response.py
block_snippets/utils.py
block_snippets/views.py
block_snippets/locale/cs/LC_MESSAGES/django.po
block_snippets/templatetags/__init__.py
block_snippets/templatetags/snippets.py
django_block_snippets.egg-info/PKG-INFO
django_block_snippets.egg-info/SOURCES.txt
django_block_snippets.egg-info/dependency_links.txt
django_block_snippets.egg-info/not-zip-safe
django_block_snippets.egg-info/requires.txt
django_block_snippets.egg-info/top_level.txt
example/__init__.py
example/manage.py
example/dj/__init__.py
example/dj/urls.py
example/dj/wsgi.py
example/dj/apps/__init__.py
example/dj/apps/app/__init__.py
example/dj/apps/app/models.py
example/dj/apps/app/views.py
example/dj/apps/app/tests/__init__.py
example/dj/apps/app/tests/snippets.py
example/dj/settings/__init__.py
example/dj/settings/base.py
example/dj/settings/settings.py